Metadata-Version: 1.0
Name: simple-distributions-v11
Version: 1.1
Summary: Gaussian and Binomial distributions
Home-page: UNKNOWN
Author: Aram hamidi
Author-email: aram1hamidi@gmail.com
License: UNKNOWN
Platform: UNKNOWN
